buscophylo
