Metadata-Version: 2.1
Name: buscophylo
Version: 1.3
Summary: BuscoPhylo is a free, online pipeline for performing BUSCO-based phylogenomic analysis. It quickly analyzes genome sequences in FASTA format and provides results ready for publication. The user-friendly interface makes it accessible for anyone to use.
Home-page: https://buscophylo.inra.org.ma/
Author: Alae-eddine Sahbou
Author-email: alae.shb147@gmail.com
License: UNKNOWN
Project-URL: Source, https://github.com/alaesahbou/BuscoPhylo
Keywords: busco phylogenomic analysis
Platform: UNKNOWN
Classifier: Programming Language :: Python :: 3
Classifier: Operating System :: OS Independent
Classifier: Intended Audience :: Science/Research
Classifier: Topic :: Scientific/Engineering :: Bio-Informatics
